/*     */ package me.dkim19375.vaultbaltop.e.e;
/*     */ 
/*     */ import java.util.UUID;
/*     */ import me.dkim19375.vaultbaltop.VaultBaltop;
/*     */ import net.milkbowl.vault.economy.Economy;
/*     */ import org.bukkit.Bukkit;
/*     */ import org.bukkit.OfflinePlayer;
/*     */ 
/*     */ 
/*     */ 
/*     */ 
/*     */ 
/*     */ 
/*     */ 
/*     */ 
/*     */ 
/*     */ 
/*     */ 
/*     */ 
/*     */ 
/*     */ 
/*     */ 
/*     */ 
/*     */ 
/*     */ 
/*     */ 
/*     */ 
/*     */ 
/*     */ 
/*     */ 
/*     */ 
/*     */ 
/*     */ 
/*     */ 
/*     */ 
/*     */ 
/*     */ 
/*     */ 
/*     */ 
/*     */ 
/*     */ 
/*     */ 
/*     */ 
/*     */ 
/*     */ 
/*     */ 
/*     */ 
/*     */ 
/*     */ 
/*     */ 
/*     */ 
/*     */ 
/*     */ 
/*     */ 
/*     */ 
/*     */ 
/*     */ 
/*     */ 
/*     */ 
/*     */ 
/*     */ 
/*     */ 
/*     */ 
/*     */ 
/*     */ 
/*     */ 
/*     */ 
/*     */ 
/*     */ 
/*     */ 
/*     */ 
/*     */ 
/*     */ 
/*     */ 
/*     */ 
/*     */ 
/*     */ 
/*     */ 
/*     */ 
/*     */ 
/*     */ 
/*     */ 
/*     */ 
/*     */ 
/*     */ 
/*     */ 
/*     */ 
/*     */ 
/*     */ 
/*     */ 
/*     */ 
/*     */ 
/*     */ 
/*     */ 
/*     */ 
/*     */ 
/*     */ 
/*     */ 
/*     */ 
/*     */ 
/*     */ 
/*     */ 
/*     */ 
/*     */ 
/*     */ 
/*     */ 
/*     */ 
/*     */ 
/*     */ 
/*     */ 
/*     */ 
/*     */ 
/*     */ 
/*     */ 
/*     */ 
/*     */ 
/*     */ 
/*     */ 
/*     */ 
/*     */ 
/*     */ 
/*     */ 
/*     */ 
/*     */ 
/*     */ 
/*     */ 
/*     */ 
/*     */ 
/*     */ 
/*     */ 
/*     */ 
/*     */ 
/*     */ 
/*     */ 
/*     */ 
/*     */ 
/*     */ 
/*     */ 
/*     */ 
/*     */ 
/*     */ 
/*     */ 
/*     */ 
/*     */ 
/*     */ 
/*     */ 
/*     */ 
/*     */ 
/*     */ 
/*     */ 
/*     */ 
/*     */ 
/*     */ 
/*     */ 
/*     */ 
/*     */ 
/*     */ 
/*     */ 
/*     */ 
/*     */ 
/*     */ 
/*     */ 
/*     */ 
/*     */ 
/*     */ 
/*     */ 
/*     */ 
/*     */ 
/*     */ 
/*     */ 
/*     */ 
/*     */ 
/*     */ 
/*     */ 
/*     */ 
/*     */ 
/*     */ 
/*     */ 
/*     */ 
/*     */ 
/*     */ 
/*     */ 
/*     */ 
/*     */ 
/*     */ 
/*     */ 
/*     */ 
/*     */ 
/*     */ 
/*     */ 
/*     */ 
/*     */ 
/*     */ 
/*     */ 
/*     */ 
/*     */ 
/*     */ 
/*     */ 
/*     */ 
/*     */ 
/*     */ 
/*     */ 
/*     */ 
/*     */ 
/*     */ 
/*     */ 
/*     */ 
/*     */ 
/*     */ 
/*     */ 
/*     */ 
/*     */ 
/*     */ 
/*     */ 
/*     */ 
/*     */ 
/*     */ 
/*     */ 
/*     */ 
/*     */ 
/*     */ public class IIIlIllIIllIIlllIIlIIIllIIllIl
/*     */ {
/*     */   public static OfflinePlayer[] IIIllIIIlIIlllIIIIlIIIlllIllIl() {
/*     */     // Byte code:
/*     */     //   0: invokestatic IIIllIIIlIIlllIIIIlIIIlllIllIl : ()Lnet/milkbowl/vault/economy/Economy;
/*     */     //   3: astore_0
/*     */     //   4: new java/util/HashMap
/*     */     //   7: dup
/*     */     //   8: invokespecial <init> : ()V
/*     */     //   11: astore_1
/*     */     //   12: invokestatic getOfflinePlayers : ()[Lorg/bukkit/OfflinePlayer;
/*     */     //   15: dup
/*     */     //   16: astore_2
/*     */     //   17: arraylength
/*     */     //   18: istore_3
/*     */     //   19: iconst_0
/*     */     //   20: iconst_1
/*     */     //   21: dup
/*     */     //   22: pop2
/*     */     //   23: dup
/*     */     //   24: istore #4
/*     */     //   26: iload_3
/*     */     //   27: if_icmpge -> 64
/*     */     //   30: aload_2
/*     */     //   31: iload #4
/*     */     //   33: aaload
/*     */     //   34: astore #5
/*     */     //   36: aload_1
/*     */     //   37: aload_0
/*     */     //   38: aload #5
/*     */     //   40: dup_x1
/*     */     //   41: iinc #4, 1
/*     */     //   44: invokeinterface getBalance : (Lorg/bukkit/OfflinePlayer;)D
/*     */     //   49: invokestatic valueOf : (D)Ljava/lang/Double;
/*     */     //   52: invokeinterface put : (Ljava/lang/Object;Ljava/lang/Object;)Ljava/lang/Object;
/*     */     //   57: pop
/*     */     //   58: iload #4
/*     */     //   60: goto -> 26
/*     */     //   63: athrow
/*     */     //   64: aload_1
/*     */     //   65: invokestatic lIlIlIIlllllIIIllIllIIlIllIIlI : (Ljava/util/Map;)Ljava/util/LinkedHashMap;
/*     */     //   68: dup
/*     */     //   69: astore_2
/*     */     //   70: invokevirtual keySet : ()Ljava/util/Set;
/*     */     //   73: dup
/*     */     //   74: astore_3
/*     */     //   75: iconst_1
/*     */     //   76: dup
/*     */     //   77: dup
/*     */     //   78: pop2
/*     */     //   79: anewarray org/bukkit/OfflinePlayer
/*     */     //   82: iconst_1
/*     */     //   83: dup
/*     */     //   84: pop2
/*     */     //   85: invokeinterface toArray : ([Ljava/lang/Object;)[Ljava/lang/Object;
/*     */     //   90: checkcast [Lorg/bukkit/OfflinePlayer;
/*     */     //   93: areturn
/*     */     // Line number table:
/*     */     //   Java source line number -> byte code offset
/*     */     //   #102	-> 0
/*     */     //   #13	-> 4
/*     */     //   #23	-> 12
/*     */     //   #193	-> 36
/*     */     //   #23	-> 57
/*     */     //   #240	-> 64
/*     */     //   #27	-> 70
/*     */     //   #185	-> 75
/*     */   }
/*     */   
/*     */   public static UUID[] IIIllIIIlIIlllIIIIlIIIlllIllIl() {
/*     */     // Byte code:
/*     */     //   0: invokestatic IIIllIIIlIIlllIIIIlIIIlllIllIl : ()Lnet/milkbowl/vault/economy/Economy;
/*     */     //   3: astore_0
/*     */     //   4: new java/util/HashMap
/*     */     //   7: dup
/*     */     //   8: invokespecial <init> : ()V
/*     */     //   11: astore_1
/*     */     //   12: invokestatic getOfflinePlayers : ()[Lorg/bukkit/OfflinePlayer;
/*     */     //   15: dup
/*     */     //   16: astore_2
/*     */     //   17: arraylength
/*     */     //   18: istore_3
/*     */     //   19: iconst_0
/*     */     //   20: iconst_1
/*     */     //   21: dup
/*     */     //   22: pop2
/*     */     //   23: dup
/*     */     //   24: istore #4
/*     */     //   26: iload_3
/*     */     //   27: if_icmpge -> 70
/*     */     //   30: aload_2
/*     */     //   31: iload #4
/*     */     //   33: aaload
/*     */     //   34: astore #5
/*     */     //   36: aload_1
/*     */     //   37: aload #5
/*     */     //   39: invokeinterface getUniqueId : ()Ljava/util/UUID;
/*     */     //   44: aload_0
/*     */     //   45: aload #5
/*     */     //   47: iinc #4, 1
/*     */     //   50: invokeinterface getBalance : (Lorg/bukkit/OfflinePlayer;)D
/*     */     //   55: invokestatic valueOf : (D)Ljava/lang/Double;
/*     */     //   58: invokeinterface put : (Ljava/lang/Object;Ljava/lang/Object;)Ljava/lang/Object;
/*     */     //   63: pop
/*     */     //   64: iload #4
/*     */     //   66: goto -> 26
/*     */     //   69: athrow
/*     */     //   70: aload_1
/*     */     //   71: invokestatic IIIllIIIlIIlllIIIIlIIIlllIllIl : (Ljava/util/Map;)Ljava/util/LinkedHashMap;
/*     */     //   74: dup
/*     */     //   75: astore_2
/*     */     //   76: invokevirtual keySet : ()Ljava/util/Set;
/*     */     //   79: dup
/*     */     //   80: astore_3
/*     */     //   81: iconst_1
/*     */     //   82: dup
/*     */     //   83: dup
/*     */     //   84: pop2
/*     */     //   85: anewarray java/util/UUID
/*     */     //   88: iconst_1
/*     */     //   89: dup
/*     */     //   90: pop2
/*     */     //   91: invokeinterface toArray : ([Ljava/lang/Object;)[Ljava/lang/Object;
/*     */     //   96: checkcast [Ljava/util/UUID;
/*     */     //   99: areturn
/*     */     // Line number table:
/*     */     //   Java source line number -> byte code offset
/*     */     //   #145	-> 0
/*     */     //   #26	-> 4
/*     */     //   #87	-> 12
/*     */     //   #176	-> 36
/*     */     //   #87	-> 63
/*     */     //   #106	-> 70
/*     */     //   #157	-> 76
/*     */     //   #241	-> 81
/*     */   }
/*     */   
/*     */   public static Double[] IIIllIIIlIIlllIIIIlIIIlllIllIl() {
/* 232 */     Economy economy = VaultBaltop.IIIllIIIlIIlllIIIIlIIIlllIllIl();
/*     */     true;
/*     */     boolean bool1 = true;
/*     */     true;
/*     */     boolean bool2 = true;
/*     */     UUID[] arrayOfUUID;
/*     */     int i = (arrayOfUUID = IIIllIIIlIIlllIIIIlIIIlllIllIl()).length;
/*     */     1;
/*     */     byte b;
/*     */     if ((b = 1) < i) {
/*     */       UUID uUID = arrayOfUUID[b];
/*     */       bool1[bool2] = Double.valueOf(economy.getBalance(Bukkit.getOfflinePlayer(uUID)));
/*     */       b++;
/*     */       true;
/*     */       bool2 = true;
/*     */     } 
/*     */     return bool1;
/*     */   }
/*     */ }


/* Location:              C:\Users\Na\Documents\IntelliJ\obfuscate\VaultBaltop-1.0.0.jar!\me\dkim19375\vaultbaltop\e\e\IIIlIllIIllIIlllIIlIIIllIIllIl.class
 * Java compiler version: 8 (52.0)
 * JD-Core Version:       1.1.3
 */